hplrv_ros/__init__.py
hplrv_ros/__main__.py
hplrv_ros/cli.py
hplrv_ros/common.py
hplrv_ros/rclpy.py
hplrv_ros/rospy.py
hplrv_ros/templates/rclpy.py.jinja
hplrv_ros/templates/rospy.py.jinja
hpl_rv_ros-1.1.0.dist-info/LICENSE
hpl_rv_ros-1.1.0.dist-info/METADATA
hpl_rv_ros-1.1.0.dist-info/WHEEL
hpl_rv_ros-1.1.0.dist-info/entry_points.txt
hpl_rv_ros-1.1.0.dist-info/top_level.txt
hpl_rv_ros-1.1.0.dist-info/RECORD
