Metadata-Version: 2.1
Name: hpl-rv-ros
Version: 1.1.0
Summary: Runtime Verification tools for ROS systems
Home-page: https://github.com/HAROS-framework/hpl-rv-ros
Author: André Santos
Author-email: haros.framework@gmail.com
License: MIT
Project-URL: Source, https://github.com/HAROS-framework/hpl-rv-ros/
Project-URL: Tracker, https://github.com/HAROS-framework/hpl-rv-ros/issues
Keywords: ros,runtime verification,runtime monitoring,code generation
Classifier: Development Status :: 4 - Beta
Classifier: Intended Audience :: Developers
Classifier: Intended Audience :: Science/Research
Classifier: License :: OSI Approved :: MIT License
Classifier: Programming Language :: Python :: 3
Classifier: Programming Language :: Python :: 3.8
Classifier: Programming Language :: Python :: 3.9
Classifier: Programming Language :: Python :: 3.10
Classifier: Programming Language :: Python :: 3 :: Only
Classifier: Topic :: Scientific/Engineering
Classifier: Topic :: Software Development
Classifier: Topic :: Software Development :: Libraries
Classifier: Topic :: Software Development :: Quality Assurance
Requires-Python: >=3.8, <4
License-File: LICENSE
Requires-Dist: hpl-rv <2.0,>=1.1.2
Requires-Dist: hpl-specs <2.0,>=1.1.2
Requires-Dist: Jinja2 >=3.1.0
Requires-Dist: ruamel.yaml >=0.17.0
Provides-Extra: dev
Requires-Dist: pytest ; extra == 'dev'
Requires-Dist: tox ; extra == 'dev'
